Metadata-Version: 2.1
Name: plugin-config-exceptions
Version: 1.2.5
Summary: More poetry to the people! One can not live on water but one can live on poetry (if there is also food and also water).
Author: Jaymz In Funnel Suit
Author-email: jaymz@kommunpoet.se
Classifier: Programming Language :: Python :: 3
Classifier: License :: OSI Approved :: MIT License
Classifier: Operating System :: OS Independent
Requires-Python: >=3.6
